__init__.py
Calculator/FortuneCalculator.py
Calculator/__init__.py
FortuneCalculator/FortuneCalculator.py
FortuneCalculator/__init__.py
Fortune_Calculator-0.0.4.dist-info/LICENSE.txt
Fortune_Calculator-0.0.4.dist-info/METADATA
Fortune_Calculator-0.0.4.dist-info/WHEEL
Fortune_Calculator-0.0.4.dist-info/top_level.txt
Fortune_Calculator-0.0.4.dist-info/RECORD
