Metadata-Version: 2.1
Name: Fortune-Calculator
Version: 0.0.4
Summary: Minecraft Fortune Calculator
Home-page: https://github.com/MisileLab/Project-MisileLab/tree/main/Small1/Ver%200.1/FortuneCalculator
Author: MisileLab
Author-email: misileminecord@gmail.com
License: MisileLab License V1.0
Platform: UNKNOWN
License-File: LICENSE.txt
